ara_cli/__init__.py
ara_cli/__main__.py
ara_cli/ara_command_action.py
ara_cli/ara_config.py
ara_cli/artefact_autofix.py
ara_cli/artefact_converter.py
ara_cli/artefact_creator.py
ara_cli/artefact_deleter.py
ara_cli/artefact_fuzzy_search.py
ara_cli/artefact_link_updater.py
ara_cli/artefact_lister.py
ara_cli/artefact_reader.py
ara_cli/artefact_renamer.py
ara_cli/artefact_scan.py
ara_cli/chat.py
ara_cli/classifier.py
ara_cli/codefusionretriever.py
ara_cli/codehierachieretriever.py
ara_cli/commandline_completer.py
ara_cli/completers.py
ara_cli/constants.py
ara_cli/directory_navigator.py
ara_cli/error_handler.py
ara_cli/file_classifier.py
ara_cli/file_lister.py
ara_cli/filename_validator.py
ara_cli/global_file_lister.py
ara_cli/list_filter.py
ara_cli/llm_utils.py
ara_cli/output_suppressor.py
ara_cli/prompt_chat.py
ara_cli/prompt_extractor.py
ara_cli/prompt_handler.py
ara_cli/prompt_rag.py
ara_cli/run_file_lister.py
ara_cli/tag_extractor.py
ara_cli/template_loader.py
ara_cli/template_manager.py
ara_cli/update_config_prompt.py
ara_cli/version.py
ara_cli/ara_subcommands/__init__.py
ara_cli/ara_subcommands/autofix.py
ara_cli/ara_subcommands/chat.py
ara_cli/ara_subcommands/classifier_directory.py
ara_cli/ara_subcommands/common.py
ara_cli/ara_subcommands/config.py
ara_cli/ara_subcommands/convert.py
ara_cli/ara_subcommands/create.py
ara_cli/ara_subcommands/delete.py
ara_cli/ara_subcommands/extract.py
ara_cli/ara_subcommands/fetch.py
ara_cli/ara_subcommands/fetch_agents.py
ara_cli/ara_subcommands/fetch_scripts.py
ara_cli/ara_subcommands/fetch_templates.py
ara_cli/ara_subcommands/list.py
ara_cli/ara_subcommands/list_tags.py
ara_cli/ara_subcommands/load.py
ara_cli/ara_subcommands/prompt.py
ara_cli/ara_subcommands/read.py
ara_cli/ara_subcommands/read_status.py
ara_cli/ara_subcommands/read_user.py
ara_cli/ara_subcommands/reconnect.py
ara_cli/ara_subcommands/rename.py
ara_cli/ara_subcommands/scan.py
ara_cli/ara_subcommands/set_status.py
ara_cli/ara_subcommands/set_user.py
ara_cli-0.1.13.4.dist-info/METADATA
ara_cli-0.1.13.4.dist-info/WHEEL
ara_cli-0.1.13.4.dist-info/entry_points.txt
ara_cli-0.1.13.4.dist-info/top_level.txt
ara_cli-0.1.13.4.dist-info/RECORD
