Metadata-Version: 2.4
Name: ara_cli
Version: 0.1.13.4
Summary: Powerful, open source command-line tool for managing, structuring and automating software development artifacts in line with Business-Driven Development (BDD) and AI-assisted processes
Requires-Dist: langfuse
Requires-Dist: litellm==1.49.7
Requires-Dist: llama-index
Requires-Dist: llama-index-llms-openai
Requires-Dist: llama-index-retrievers-bm25
Requires-Dist: openai
Requires-Dist: markdown-it-py
Requires-Dist: json-repair
Requires-Dist: argparse
Requires-Dist: argcomplete
Requires-Dist: cmd2>=2.5
Requires-Dist: charset-normalizer
Requires-Dist: pydantic
Requires-Dist: pydantic_ai
Requires-Dist: python-docx
Requires-Dist: pymupdf4llm
Requires-Dist: typer
Requires-Dist: psutil
Requires-Dist: requests
Requires-Dist: rich
Dynamic: description
Dynamic: description-content-type
Dynamic: requires-dist
Dynamic: summary
